mcp_server_shell/__init__.py
mcp_server_shell/__main__.py
mcp_server_shell/server.py
mcp_server_shell-0.1.0.dist-info/METADATA
mcp_server_shell-0.1.0.dist-info/WHEEL
mcp_server_shell-0.1.0.dist-info/entry_points.txt
mcp_server_shell-0.1.0.dist-info/RECORD
