Metadata-Version: 2.3
Name: mcp-server-shell
Version: 0.1.0
Summary: A Model Context Protocol server providing shell command execution capabilities for LLMs
License: MIT
Keywords: command,llm,mcp,shell
Classifier: Development Status :: 4 - Beta
Classifier: Intended Audience :: Developers
Classifier: License :: OSI Approved :: MIT License
Classifier: Programming Language :: Python :: 3
Classifier: Programming Language :: Python :: 3.10
Requires-Python: >=3.10
Requires-Dist: mcp>=1.0.0
Requires-Dist: pydantic>=2.0.0
